arabic_buckwalter_transliteration/__init__.py
arabic_buckwalter_transliteration/transliteration.py
tests/__init__.py
tests/test_transliteration.py
arabic_buckwalter_transliteration-1.0.5.dist-info/LICENSE
arabic_buckwalter_transliteration-1.0.5.dist-info/METADATA
arabic_buckwalter_transliteration-1.0.5.dist-info/WHEEL
arabic_buckwalter_transliteration-1.0.5.dist-info/top_level.txt
arabic_buckwalter_transliteration-1.0.5.dist-info/RECORD
