Metadata-Version: 2.1
Name: arabic-buckwalter-transliteration
Version: 1.0.5
Summary: A Python package to convert Arabic text to Buckwalter transliteration and vice versa
Author: Hayder Kharrufa
Author-email: 
Classifier: Programming Language :: Python :: 3
Classifier: License :: OSI Approved :: MIT License
Classifier: Operating System :: OS Independent
Requires-Python: >=3.6
License-File: LICENSE
